.editorconfig
.gitignore
.gitlab-ci.yml
README.rst
publish.settings.sh
publish.sh
pyproject.toml
tsconfig.json
.idea/modules.xml
.idea/peek-plugin-inbox.iml
.idea/inspectionProfiles/Project_Default.xml
.idea/inspectionProfiles/profiles_settings.xml
docs/conf.py
docs/index.rst
docs/rtfd_requirements.txt
docs/watch-docs.sh
docs/_static/.gitkeep
docs/api/index_api.rst
docs/api_autodoc/peek_plugin_inbox/peek_plugin_inbox.rst
docs/api_autodoc/peek_plugin_inbox/peek_plugin_inbox.server.rst
docs/overview/Inbox-DesignDiagram.jpg
docs/overview/overview.rst
peek_plugin_inbox/TempUnitTest.py
peek_plugin_inbox/__init__.py
peek_plugin_inbox/plugin_package.json
peek_plugin_inbox.egg-info/PKG-INFO
peek_plugin_inbox.egg-info/SOURCES.txt
peek_plugin_inbox.egg-info/dependency_links.txt
peek_plugin_inbox.egg-info/requires.txt
peek_plugin_inbox.egg-info/top_level.txt
peek_plugin_inbox/_private/PluginNames.py
peek_plugin_inbox/_private/__init__.py
peek_plugin_inbox/_private/alembic.ini
peek_plugin_inbox/_private/admin-app/plugin-inbox.module.ts
peek_plugin_inbox/_private/admin-app/components/activity-list/admin-activity-list.component.html
peek_plugin_inbox/_private/admin-app/components/activity-list/admin-activity-list.component.scss
peek_plugin_inbox/_private/admin-app/components/activity-list/admin-activity-list.component.ts
peek_plugin_inbox/_private/admin-app/components/plugin-inbox-page/plugin-inbox-page.component.html
peek_plugin_inbox/_private/admin-app/components/plugin-inbox-page/plugin-inbox-page.component.scss
peek_plugin_inbox/_private/admin-app/components/plugin-inbox-page/plugin-inbox-page.component.ts
peek_plugin_inbox/_private/admin-app/components/send-test-activity/send-test-activity.component.html
peek_plugin_inbox/_private/admin-app/components/send-test-activity/send-test-activity.component.scss
peek_plugin_inbox/_private/admin-app/components/send-test-activity/send-test-activity.component.ts
peek_plugin_inbox/_private/admin-app/components/send-test-task/send-test-task.component.html
peek_plugin_inbox/_private/admin-app/components/send-test-task/send-test-task.component.scss
peek_plugin_inbox/_private/admin-app/components/send-test-task/send-test-task.component.ts
