Metadata-Version: 2.4
Name: peek-plugin-inbox
Version: 5.0.4
Summary: Peek Plugin Inbox - task management for Peek users
Author-email: Synerty <contact@synerty.com>
Project-URL: Homepage, https://github.com/Synerty/peek-plugin-inbox
Keywords: Peek,Python,Platform,synerty
Requires-Dist: peek-plugin-base==5.0.4
